corrupted_text/__init__.py
corrupted_text/text_corruptor.py
corrupted_text-0.2.0.dist-info/LICENSE
corrupted_text-0.2.0.dist-info/METADATA
corrupted_text-0.2.0.dist-info/WHEEL
corrupted_text-0.2.0.dist-info/top_level.txt
corrupted_text-0.2.0.dist-info/RECORD
