Metadata-Version: 2.1
Name: corrupted-text
Version: 0.2.0
Summary: Corruption of text datasets; model-independent and inspired byreal-world corruption causes.
Home-page: https://github.com/testingautomated-usi/corrupted-text
Author: Michael Weiss
Author-email: michael.weiss@usi.ch
License: MIT
Platform: UNKNOWN
Classifier: Programming Language :: Python :: 3
Classifier: License :: OSI Approved :: MIT License
Classifier: Operating System :: OS Independent
Requires-Dist: numpy (>=1.16.4)
Requires-Dist: polyleven (==0.7)
Provides-Extra: acc_measurement
Requires-Dist: datasets (>=1.0.0) ; extra == 'acc_measurement'
Requires-Dist: tensorflow (>=2.6.0) ; extra == 'acc_measurement'
Provides-Extra: lint
Requires-Dist: black (==22.3.0) ; extra == 'lint'
Requires-Dist: docstr-coverage (==2.2.0) ; extra == 'lint'
Requires-Dist: flake8 (==3.8.2) ; extra == 'lint'
Requires-Dist: isort (==5.6.4) ; extra == 'lint'
Provides-Extra: test
Requires-Dist: datasets (>=1.0.0) ; extra == 'test'
Requires-Dist: pytest (>=6.2.5) ; extra == 'test'
